__init__.py
rag_core_openai.py
mcp_rag/__init__.py
mcp_rag/cli.py
mcp_rag/server.py
mcp_rag/web.py
models/__init__.py
models/document_model.py
models/metadata_model.py
services/__init__.py
services/cloud_openai.py
tools/__init__.py
tools/document_tools.py
tools/search_tools.py
utils/__init__.py
utils/config.py
utils/logger.py
mcp_rag_fastmcp-0.3.17.dist-info/METADATA
mcp_rag_fastmcp-0.3.17.dist-info/WHEEL
mcp_rag_fastmcp-0.3.17.dist-info/entry_points.txt
mcp_rag_fastmcp-0.3.17.dist-info/top_level.txt
mcp_rag_fastmcp-0.3.17.dist-info/RECORD
