Metadata-Version: 2.4
Name: mcp-rag-fastmcp
Version: 0.3.17
Summary: Add your description here
Project-URL: Homepage, https://github.com/fastmcp-me/mcp-rag#readme
Project-URL: Repository, https://github.com/fastmcp-me/mcp-rag.git
Project-URL: Issues, https://github.com/fastmcp-me/mcp-rag/issues
Requires-Python: >=3.13
Requires-Dist: python-dotenv>=1.0.1
Requires-Dist: openai>=1.40.0
Requires-Dist: volcengine-python-sdk[ark]>=1.0.0
Requires-Dist: mcp>=1.12.4
Requires-Dist: requests>=2.32.3
Requires-Dist: rich>=14.1.0
Requires-Dist: tqdm>=4.67.1
Requires-Dist: flask>=3.0.0
